{
  "ultima_atualizacao": "2026-07-07T11:21:42.039247",
  "dede": {
    "nome": "Dede",
    "cor": "#3B82F6",
    "livros": [
      {
        "id": "herois-vol9",
        "nome": "HEROIS VOL 9",
        "total_capitulos": 34,
        "coordenadores": [
          {
            "id": "irene-sa",
            "nome": "COORD-IRENE DE SA",
            "autores": [
              {
                "nome": "Juliano Serotini",
                "status": "concluido",
                "data": "2026-06-23",
                "creditos": 16.0,
                "foto": true
              },
              {
                "nome": "Sandro Botta",
                "status": "concluido",
                "data": "2026-06-23",
                "creditos": 2.59,
                "foto": true
              },
              {
                "nome": "Carla Cazella",
                "status": "concluido",
                "data": "2026-06-24",
                "creditos": 2.79,
                "foto": true
              },
              {
                "nome": "Claudimara Zanchetta",
                "status": "concluido",
                "data": "2026-06-24",
                "creditos": 2.7,
                "foto": true
              },
              {
                "nome": "Eliane Mirandolli",
                "status": "concluido",
                "data": "2026-06-24",
                "creditos": 6.17,
                "foto": true
              },
              {
                "nome": "Gelsi Moschetta",
                "status": "concluido",
                "data": "2026-06-24",
                "creditos": 2.1,
                "foto": true
              },
              {
                "nome": "Gilvana Botta",
                "status": "concluido",
                "data": "2026-06-24",
                "creditos": 3.2,
                "foto": true
              },
              {
                "nome": "Gizely Delmonico",
                "status": "concluido",
                "data": "2026-06-24",
                "creditos": 2.8,
                "foto": true
              },
              {
                "nome": "Irene Sa Affolter",
                "status": "concluido",
                "data": "2026-06-24",
                "creditos": 2.4,
                "foto": true
              },
              {
                "nome": "Katia Boni",
                "status": "concluido",
                "data": "2026-06-24",
                "creditos": 2.1,
                "foto": true
              },
              {
                "nome": "Luiz Paulo",
                "status": "concluido",
                "data": "2026-06-24",
                "creditos": 2.5,
                "foto": false
              },
              {
                "nome": "Mariana Cozer Siviero",
                "status": "concluido",
                "data": "2026-06-24",
                "creditos": 1.8,
                "foto": true
              },
              {
                "nome": "Mauro Tibola",
                "status": "concluido",
                "data": "2026-06-24",
                "creditos": 1.9,
                "foto": true
              },
              {
                "nome": "Monica Tavares de Barros",
                "status": "concluido",
                "data": "2026-06-24",
                "creditos": 2.3,
                "foto": true
              },
              {
                "nome": "Rosana Titonelli",
                "status": "concluido",
                "data": "2026-06-24",
                "creditos": 2.2,
                "foto": true
              },
              {
                "nome": "fabricia gedoz",
                "status": "concluido",
                "foto": true,
                "data": "2026-07-02",
                "creditos": 9
              },
              {
                "nome": "nadia cristina bonai",
                "status": "concluido",
                "foto": true,
                "data": "2026-07-02",
                "creditos": 14
              },
              {
                "nome": "paula franzoni",
                "status": "concluido",
                "foto": true,
                "data": "2026-07-02",
                "creditos": 5
              },
              {
                "nome": "- Juliano Serotini",
                "status": "concluido",
                "foto": true,
                "data": "2026-07-02",
                "creditos": 0
              },
              {
                "nome": "- Sandro Botta  - Lilian - Arte Hile",
                "status": "concluido",
                "foto": true,
                "data": "2026-07-02",
                "creditos": 0
              },
              {
                "nome": "Cap. Carla atualizado",
                "status": "concluido",
                "foto": true,
                "data": "2026-07-02",
                "creditos": 0
              },
              {
                "nome": "Irene sá affolter",
                "status": "concluido",
                "foto": true,
                "data": "2026-07-02",
                "creditos": 0
              },
              {
                "nome": "NELCI TEREZINHA",
                "status": "concluido",
                "foto": true,
                "data": "2026-07-02",
                "creditos": 0
              },
              {
                "nome": "Rosana Titonelli -1",
                "status": "concluido",
                "foto": true,
                "data": "2026-07-02",
                "creditos": 0
              }
            ]
          },
          {
            "id": "coord-juraci",
            "nome": "COORD-JURACI",
            "autores": [
              {
                "nome": "Jose Joelson dos Santos",
                "status": "concluido",
                "data": "2026-07-02",
                "creditos": 2,
                "foto": true
              },
              {
                "nome": "Juraci",
                "status": "pendente",
                "foto": false,
                "data": null,
                "creditos": 0
              }
            ]
          },
          {
            "id": "coord-cris-farias",
            "nome": "COORD-CRIS FARIAS",
            "autores": [
              {
                "nome": "Crystiane Angelica Briel de Mello",
                "status": "concluido",
                "data": "2026-06-27",
                "creditos": 1.26,
                "foto": true
              },
              {
                "nome": "Crystiane Farias",
                "status": "concluido",
                "data": "2026-06-27",
                "creditos": 1.26,
                "foto": true
              },
              {
                "nome": "Giuseppina Maria Fulco",
                "status": "concluido",
                "data": "2026-06-27",
                "creditos": 1.26,
                "foto": true
              },
              {
                "nome": "Maria Divina Silva e Silva Brasil",
                "status": "concluido",
                "data": "2026-06-27",
                "creditos": 1.26,
                "foto": true
              },
              {
                "nome": "Rosangela Aparecida da Silva",
                "status": "pendente",
                "data": null,
                "creditos": 0,
                "foto": false
              },
              {
                "nome": "Suelen de Araujo Borges",
                "status": "concluido",
                "data": "2026-06-27",
                "creditos": 1.26,
                "foto": true
              },
              {
                "nome": "Telma Conceicao Alves Ferreira Soares",
                "status": "pendente",
                "data": null,
                "creditos": 0,
                "foto": false
              },
              {
                "nome": "juliana macedo",
                "status": "concluido",
                "foto": true,
                "data": "2026-07-02",
                "creditos": 2
              },
              {
                "nome": "Dr Paula Melo",
                "status": "concluido",
                "foto": true,
                "data": "2026-07-08",
                "creditos": 0
              }
            ]
          },
          {
            "id": "coord-chico-jr",
            "nome": "COORD-CHICO JR",
            "autores": [
              {
                "nome": "Antonia Gelza Paulo Ferreira",
                "status": "concluido",
                "data": "2026-06-27",
                "creditos": 1.26,
                "foto": true
              },
              {
                "nome": "Cicero Ronuery Rodrigues",
                "status": "concluido",
                "data": "2026-06-27",
                "creditos": 1.26,
                "foto": true
              },
              {
                "nome": "Eliana Alves Santos e Silva",
                "status": "concluido",
                "data": "2026-06-27",
                "creditos": 1.26,
                "foto": true
              },
              {
                "nome": "Ivignne Lowis Leite dos Reis",
                "status": "concluido",
                "data": "2026-06-27",
                "creditos": 1.26,
                "foto": true
              },
              {
                "nome": "Leandro Silva Almeida",
                "status": "concluido",
                "data": "2026-06-27",
                "creditos": 1.26,
                "foto": true
              },
              {
                "nome": "Luan Lopes Oliveira",
                "status": "concluido",
                "data": "2026-06-27",
                "creditos": 1.26,
                "foto": true
              },
              {
                "nome": "Luis Eduardo",
                "status": "concluido",
                "data": "2026-07-02",
                "creditos": 3,
                "foto": true
              },
              {
                "nome": "Roberta Mateus Pereira",
                "status": "concluido",
                "data": "2026-06-27",
                "creditos": 1.26,
                "foto": true
              },
              {
                "nome": "Rondinele dos Santos Brasil",
                "status": "concluido",
                "data": "2026-06-27",
                "creditos": 1.26,
                "foto": true
              },
              {
                "nome": "Tarcisio Sampaio",
                "status": "concluido",
                "data": "2026-06-27",
                "creditos": 1.26,
                "foto": true
              },
              {
                "nome": "William de Carvalho",
                "status": "concluido",
                "data": "2026-06-27",
                "creditos": 1.26,
                "foto": true
              },
              {
                "nome": "Chico Jr",
                "status": "concluido",
                "data": "2026-06-27",
                "creditos": 1.26,
                "foto": true
              },
              {
                "nome": "yasmin americo",
                "status": "concluido",
                "foto": true,
                "data": "2026-07-02",
                "creditos": 5
              }
            ]
          },
          {
            "nome": "COORD-RADEMAR DE SA",
            "autores": [
              {
                "nome": "RADEMAR DE SA",
                "status": "concluido",
                "foto": true,
                "data": "2026-07-07",
                "creditos": 3
              }
            ]
          }
        ]
      },
      {
        "id": "entre-diagnostico-vida",
        "nome": "Entre o Diagnóstico e a Vida",
        "total_capitulos": 26,
        "coordenadores": [
          {
            "id": "coord-alice",
            "nome": "Alice Correia",
            "autores": [
              {
                "nome": "Carla Vargas Dias",
                "status": "concluido",
                "data": "2026-06-27",
                "creditos": 1.26,
                "foto": true
              },
              {
                "nome": "Carlos Henrique de Jesus",
                "status": "concluido",
                "data": "2026-06-27",
                "creditos": 1.26,
                "foto": true
              },
              {
                "nome": "Dr Giovanni Melo de Oliveira",
                "status": "concluido",
                "data": "2026-07-02",
                "creditos": 3,
                "foto": true
              },
              {
                "nome": "Lorena Rios Ferraz de Almeida",
                "status": "concluido",
                "data": "2026-07-03",
                "creditos": 4,
                "foto": true
              },
              {
                "nome": "Priscila Andrade Silva",
                "status": "concluido",
                "data": "2026-06-27",
                "creditos": 1.26,
                "foto": true
              },
              {
                "nome": "Rapuzel Jastro Mantovani",
                "status": "pendente",
                "data": null,
                "creditos": 0,
                "foto": false
              },
              {
                "nome": "Thaisa de Araujo Ferreira",
                "status": "concluido",
                "data": "2026-07-03",
                "creditos": 7,
                "foto": true
              },
              {
                "nome": "Valdineia Machado Lages Ferrazi",
                "status": "concluido",
                "data": "2026-07-02",
                "creditos": 13,
                "foto": true
              },
              {
                "nome": "Vanda Oliveira Lauret dos Anjos",
                "status": "concluido",
                "data": "2026-07-02",
                "creditos": 13,
                "foto": true
              },
              {
                "nome": "Alice Correia",
                "status": "concluido",
                "foto": true,
                "data": "2026-07-02",
                "creditos": 7
              },
              {
                "nome": "gabrielle  soares",
                "status": "concluido",
                "foto": true,
                "data": "2026-07-03",
                "creditos": 3
              },
              {
                "nome": "kamilla ragassi",
                "status": "concluido",
                "foto": true,
                "data": "2026-07-03",
                "creditos": 45
              },
              {
                "nome": "ylana paravidino",
                "status": "concluido",
                "foto": true,
                "data": "2026-07-08",
                "creditos": 10
              }
            ]
          },
          {
            "id": "coord-ariane",
            "nome": "Ariane",
            "autores": [
              {
                "nome": "Beatriz Damasceno Avaria",
                "status": "concluido",
                "data": "2026-06-27",
                "creditos": 1.26,
                "foto": true
              },
              {
                "nome": "Emerson dos Santos Duarte Mafia",
                "status": "concluido",
                "data": "2026-07-02",
                "creditos": 14,
                "foto": true
              },
              {
                "nome": "Humberto Jander de Souza",
                "status": "concluido",
                "data": "2026-07-02",
                "creditos": 2,
                "foto": true
              },
              {
                "nome": "Joelana Magali de Oliveira",
                "status": "concluido",
                "data": "2026-07-03",
                "creditos": 3,
                "foto": true
              },
              {
                "nome": "Julia Fialho Pessoa Candido",
                "status": "concluido",
                "data": "2026-07-02",
                "creditos": 4,
                "foto": true
              },
              {
                "nome": "Kerlen Teixeira do Rego Martins Ferreira",
                "status": "concluido",
                "data": "2026-07-03",
                "creditos": 30,
                "foto": true
              },
              {
                "nome": "Millena Selva Medeiros Garonce",
                "status": "concluido",
                "data": "2026-06-27",
                "creditos": 1.26,
                "foto": true
              },
              {
                "nome": "Neiliana Medeiros de Souza Rabelo",
                "status": "concluido",
                "data": "2026-06-27",
                "creditos": 1.26,
                "foto": true
              },
              {
                "nome": "Octavio Amazonas Mendes Almeida",
                "status": "concluido",
                "data": "2026-07-02",
                "creditos": 5,
                "foto": true
              },
              {
                "nome": "Priscila Carla Alves",
                "status": "concluido",
                "data": "2026-07-02",
                "creditos": 0,
                "foto": true
              },
              {
                "nome": "Sabrina Andrade Novaes",
                "status": "concluido",
                "data": "2026-06-27",
                "creditos": 1.26,
                "foto": true
              },
              {
                "nome": "Tayna de Mello Reis Silva",
                "status": "concluido",
                "data": "2026-06-27",
                "creditos": 1.26,
                "foto": true
              },
              {
                "nome": "Vanessa Cristina Da Silva Jardim",
                "status": "concluido",
                "data": "2026-07-02",
                "creditos": 0,
                "foto": true
              },
              {
                "nome": "Ariane",
                "status": "concluido",
                "foto": true,
                "data": "2026-07-02",
                "creditos": 1
              }
            ]
          },
          {
            "id": "coord-matheus",
            "nome": "Matheus Souza",
            "autores": [
              {
                "nome": "Joyce Dias",
                "status": "concluido",
                "data": "2026-06-27",
                "creditos": 1.26,
                "foto": true
              },
              {
                "nome": "Silvia Patricia Rone Alves",
                "status": "concluido",
                "data": "2026-07-02",
                "creditos": 8,
                "foto": true
              },
              {
                "nome": "rosane araujo",
                "status": "concluido",
                "data": "2026-07-02",
                "creditos": 5,
                "foto": true
              },
              {
                "nome": "Matheus Souza",
                "status": "concluido",
                "foto": true,
                "data": "2026-07-02",
                "creditos": 0
              }
            ]
          },
          {
            "id": "coord-zenaira",
            "nome": "Zenaira",
            "autores": [
              {
                "nome": "Andreza Valadares Vinagre",
                "status": "concluido",
                "data": "2026-07-08",
                "creditos": 3,
                "foto": true
              },
              {
                "nome": "Gabrielle Christine de Sousa Soares",
                "status": "pendente",
                "data": null,
                "creditos": 0,
                "foto": false
              },
              {
                "nome": "Zenaira",
                "status": "pendente",
                "foto": false,
                "data": null,
                "creditos": 0
              },
              {
                "nome": "Rachel Mollyna",
                "status": "concluido",
                "foto": true,
                "data": "2026-07-08",
                "creditos": 2
              }
            ]
          }
        ]
      },
      {
        "id": "gigantes-pt",
        "nome": "Gigantes Nascem da Queda - PT",
        "total_capitulos": 22,
        "coordenadores": [
          {
            "id": "coord-fran",
            "nome": "Fran Backer",
            "autores": [
              {
                "nome": "Camila Bongiovanni Watanabe",
                "status": "concluido",
                "data": "2026-07-03",
                "creditos": 4,
                "foto": true
              },
              {
                "nome": "Fran Backer",
                "status": "concluido",
                "foto": true,
                "data": "2026-07-03",
                "creditos": 2
              }
            ]
          },
          {
            "id": "coord-marcio",
            "nome": "Marcio Okabe",
            "autores": [
              {
                "nome": "Marcio Okabe",
                "status": "concluido",
                "foto": true,
                "data": "2026-07-07",
                "creditos": 4
              }
            ]
          },
          {
            "id": "coord-raquel",
            "nome": "Raquel",
            "autores": [
              {
                "nome": "Alice Marimon",
                "status": "concluido",
                "data": "2026-07-07",
                "creditos": 3,
                "foto": false
              },
              {
                "nome": "Cesar de Carvalho Pereira",
                "status": "concluido",
                "data": "2026-06-27",
                "creditos": 1.26,
                "foto": true
              },
              {
                "nome": "Daphne Chicarino",
                "status": "concluido",
                "data": "2026-06-27",
                "creditos": 1.26,
                "foto": true
              },
              {
                "nome": "Joselane Pinheiro Moraes",
                "status": "concluido",
                "data": "2026-07-02",
                "creditos": 4,
                "foto": true
              },
              {
                "nome": "Karina Davina Marcondes Barros",
                "status": "concluido",
                "data": "2026-07-04",
                "creditos": 14,
                "foto": true
              },
              {
                "nome": "Leonardo Milner",
                "status": "concluido",
                "data": "2026-06-27",
                "creditos": 1.26,
                "foto": true
              },
              {
                "nome": "Lucia Raquel Macamo Cilio",
                "status": "concluido",
                "data": "2026-06-27",
                "creditos": 1.26,
                "foto": true
              },
              {
                "nome": "Luciana Moreno",
                "status": "concluido",
                "foto": true,
                "data": "2026-07-02",
                "creditos": 7
              },
              {
                "nome": "Luciane Alves de Carvalho Miranda",
                "status": "concluido",
                "foto": true,
                "data": "2026-07-07",
                "creditos": 6
              },
              {
                "nome": "Mariana Soares Santos",
                "status": "concluido",
                "data": "2026-06-27",
                "creditos": 1.26,
                "foto": true
              },
              {
                "nome": "Pedro Sheneider",
                "status": "concluido",
                "data": "2026-07-02",
                "creditos": 1,
                "foto": true
              },
              {
                "nome": "Raphael Lopes Motta",
                "status": "concluido",
                "data": "2026-06-27",
                "creditos": 1.26,
                "foto": true
              },
              {
                "nome": "Samir Ali Tarif",
                "status": "concluido",
                "data": "2026-07-02",
                "creditos": 2,
                "foto": true
              },
              {
                "nome": "Sandra Rita Samaritano",
                "status": "concluido",
                "data": "2026-06-27",
                "creditos": 1.26,
                "foto": true
              },
              {
                "nome": "Wendi Flavia Martins Caetano",
                "status": "concluido",
                "data": "2026-06-27",
                "creditos": 1.26,
                "foto": true
              },
              {
                "nome": "dr francine cruz",
                "status": "concluido",
                "foto": true,
                "data": "2026-07-07",
                "creditos": 0
              },
              {
                "nome": "marcia inati de lucca",
                "status": "concluido",
                "foto": true,
                "data": "2026-07-07",
                "creditos": 2
              }
            ]
          },
          {
            "id": "coord-saionara",
            "nome": "Saionara",
            "autores": [
              {
                "nome": "Ana Cristina Nicolau Torres",
                "status": "concluido",
                "data": "2026-06-27",
                "creditos": 1.26,
                "foto": true
              },
              {
                "nome": "Elane Daudt Ribeiro",
                "status": "pendente",
                "data": null,
                "creditos": 0,
                "foto": false
              },
              {
                "nome": "Lia Siqueira de Souza",
                "status": "pendente",
                "data": null,
                "creditos": 0,
                "foto": false
              },
              {
                "nome": "Luiza Daudt Ribeiro",
                "status": "concluido",
                "data": "2026-06-27",
                "creditos": 1.26,
                "foto": true
              },
              {
                "nome": "Paula Correa Furtado Pereira",
                "status": "concluido",
                "data": "2026-06-27",
                "creditos": 1.26,
                "foto": true
              },
              {
                "nome": "Thalita Muniz Melo",
                "status": "concluido",
                "data": "2026-07-03",
                "creditos": 5,
                "foto": true
              },
              {
                "nome": "saionara menezes",
                "status": "concluido",
                "foto": true,
                "data": "2026-07-02",
                "creditos": 5
              },
              {
                "nome": "joao miguel",
                "status": "concluido",
                "foto": true,
                "data": "2026-07-07",
                "creditos": 47
              }
            ]
          },
          {
            "nome": "juraci",
            "autores": [
              {
                "nome": "joelson santos",
                "status": "concluido",
                "foto": true,
                "data": "2026-07-03",
                "creditos": 1
              },
              {
                "nome": "juraci",
                "status": "concluido",
                "foto": true,
                "data": "2026-07-03",
                "creditos": 1
              },
              {
                "nome": "roseli santana",
                "status": "concluido",
                "foto": true,
                "data": "2026-07-03",
                "creditos": 2
              }
            ]
          }
        ]
      },
      {
        "id": "gigantes-sp",
        "nome": "Gigantes Nascem da Queda - SP",
        "total_capitulos": 26,
        "coordenadores": [
          {
            "id": "coord-adriano",
            "nome": "Adriano Moleiro",
            "autores": [
              {
                "nome": "Carlos Alcarde",
                "status": "concluido",
                "data": "2026-06-27",
                "creditos": 1.26,
                "foto": true
              },
              {
                "nome": "Daiane de Souza Moleiro",
                "status": "concluido",
                "data": "2026-07-04",
                "creditos": 5,
                "foto": true
              },
              {
                "nome": "Daniel Taketa",
                "status": "concluido",
                "data": "2026-06-27",
                "creditos": 1.26,
                "foto": true
              },
              {
                "nome": "Elaine Cristina da Silva Martins",
                "status": "concluido",
                "data": "2026-07-02",
                "creditos": 1,
                "foto": true
              },
              {
                "nome": "Helen Caroline Grechi",
                "status": "concluido",
                "data": "2026-07-02",
                "creditos": 7,
                "foto": true
              },
              {
                "nome": "Helio Sluzek Abrao",
                "status": "concluido",
                "data": "2026-07-02",
                "creditos": 0,
                "foto": true
              },
              {
                "nome": "Jaziel Ferreira dos Santos",
                "status": "concluido",
                "data": "2026-07-02",
                "creditos": 1,
                "foto": true
              },
              {
                "nome": "Juliana Rissi da Cruz",
                "status": "concluido",
                "data": "2026-06-27",
                "creditos": 1.26,
                "foto": true
              },
              {
                "nome": "Lucyane Casagrande",
                "status": "concluido",
                "data": "2026-07-02",
                "creditos": 0,
                "foto": true
              },
              {
                "nome": "Marcos Roberto de Oliveira",
                "status": "concluido",
                "data": "2026-06-27",
                "creditos": 1.26,
                "foto": true
              },
              {
                "nome": "Adriano Moleiro",
                "status": "concluido",
                "foto": true,
                "data": "2026-07-02",
                "creditos": 3
              },
              {
                "nome": "cintia borin",
                "status": "concluido",
                "foto": true,
                "data": "2026-07-02",
                "creditos": 6
              },
              {
                "nome": "alaor pedro",
                "status": "concluido",
                "foto": true,
                "data": "2026-07-03",
                "creditos": 3
              }
            ]
          },
          {
            "id": "coord-cidinha",
            "nome": "Cidinha Perez",
            "autores": [
              {
                "nome": "Andrea Vieira Scarpa Ventura",
                "status": "concluido",
                "data": "2026-06-27",
                "creditos": 1.26,
                "foto": true
              },
              {
                "nome": "Cibele Fischer Mendonca",
                "status": "concluido",
                "data": "2026-06-27",
                "creditos": 1.26,
                "foto": true
              },
              {
                "nome": "Danielle de Souza Ribas",
                "status": "concluido",
                "data": "2026-07-03",
                "creditos": 5,
                "foto": true
              },
              {
                "nome": "Deusa Dominique de Oliveira Brioni",
                "status": "concluido",
                "data": "2026-07-07",
                "creditos": 4,
                "foto": true
              },
              {
                "nome": "Eliude da Silva Trindade",
                "status": "concluido",
                "data": "2026-07-02",
                "creditos": 0,
                "foto": true
              },
              {
                "nome": "Erica Galhardo",
                "status": "concluido",
                "data": "2026-07-02",
                "creditos": 0,
                "foto": true
              },
              {
                "nome": "Fabiana Silva Goncalves Ferreira",
                "status": "concluido",
                "data": "2026-07-03",
                "creditos": 8,
                "foto": true
              },
              {
                "nome": "Guilherme Jose Bouzani de Campos Ferreira",
                "status": "concluido",
                "data": "2026-07-02",
                "creditos": 2,
                "foto": true
              },
              {
                "nome": "Cidinha Perez",
                "status": "concluido",
                "foto": true,
                "data": "2026-07-02",
                "creditos": 4
              }
            ]
          },
          {
            "id": "coord-danielle",
            "nome": "Danielle Roberta",
            "autores": [
              {
                "nome": "Lidinalva Silva de Sousa Gama",
                "status": "concluido",
                "data": "2026-07-03",
                "creditos": 7,
                "foto": true
              },
              {
                "nome": "Danielle Roberta",
                "status": "pendente",
                "foto": false,
                "data": null,
                "creditos": 0
              }
            ]
          },
          {
            "id": "coord-karolina",
            "nome": "Karolina Emanoel",
            "autores": [
              {
                "nome": "Dinarleia de Jesus Costa Rocha Ribeiro",
                "status": "concluido",
                "data": "2026-07-02",
                "creditos": 7,
                "foto": true
              },
              {
                "nome": "Joyce Batista de Souza",
                "status": "concluido",
                "data": "2026-07-07",
                "creditos": 1,
                "foto": true
              },
              {
                "nome": "Matheus Queiroz Maciel",
                "status": "concluido",
                "data": "2026-07-07",
                "creditos": 4,
                "foto": true
              },
              {
                "nome": "Patricia Anastacio",
                "status": "concluido",
                "data": "2026-07-08",
                "creditos": 5,
                "foto": true
              },
              {
                "nome": "Tharsila Tawany Neves Strambeck da Costa",
                "status": "concluido",
                "data": "2026-06-27",
                "creditos": 1.26,
                "foto": true
              },
              {
                "nome": "bianca de souza coutinho",
                "status": "concluido",
                "foto": true,
                "data": "2026-07-02",
                "creditos": 6
              },
              {
                "nome": "gleiciane aparecida",
                "status": "concluido",
                "foto": true,
                "data": "2026-07-02",
                "creditos": 14
              },
              {
                "nome": "Karolina Emanoel",
                "status": "concluido",
                "foto": true,
                "data": "2026-07-02",
                "creditos": 12
              },
              {
                "nome": "larissa dias",
                "status": "concluido",
                "foto": true,
                "data": "2026-07-02",
                "creditos": 2
              },
              {
                "nome": "leticia gomes",
                "status": "concluido",
                "foto": true,
                "data": "2026-07-02",
                "creditos": 10
              },
              {
                "nome": "tatiane golçalves",
                "status": "concluido",
                "foto": true,
                "data": "2026-07-02",
                "creditos": 16
              },
              {
                "nome": "dayse de souza kubis",
                "status": "pendente",
                "foto": false,
                "data": null,
                "creditos": 0
              }
            ]
          },
          {
            "id": "coord-malu",
            "nome": "Malu",
            "autores": [
              {
                "nome": "Claudeilene Leite Gomes",
                "status": "pendente",
                "data": null,
                "creditos": 0,
                "foto": false
              },
              {
                "nome": "Malu",
                "status": "pendente",
                "foto": false,
                "data": null,
                "creditos": 0
              }
            ]
          },
          {
            "id": "coord-sonia",
            "nome": "Sonia",
            "autores": [
              {
                "nome": "Cris",
                "status": "pendente",
                "data": null,
                "creditos": 0,
                "foto": false
              },
              {
                "nome": "Sonia",
                "status": "pendente",
                "foto": false,
                "data": null,
                "creditos": 0
              }
            ]
          }
        ]
      },
      {
        "id": "enigmas-da-mente",
        "nome": "Enigmas da Mente",
        "total_capitulos": 18,
        "coordenadores": [
          {
            "id": "coord-dr-claudio",
            "nome": "Dr Claudio",
            "autores": [
              {
                "nome": "Francisco Guilhien Gomes Junior",
                "status": "concluido",
                "data": "2026-07-02",
                "creditos": 0,
                "foto": true
              },
              {
                "nome": "Ivo Lavor",
                "status": "concluido",
                "data": "2026-07-04",
                "creditos": 1,
                "foto": true
              },
              {
                "nome": "Dr Claudio",
                "status": "concluido",
                "foto": true,
                "data": "2026-07-02",
                "creditos": 0
              }
            ]
          },
          {
            "id": "coord-maria-cecilia",
            "nome": "Maria Cecilia",
            "autores": [
              {
                "nome": "Yasmin Bastos Rosa",
                "status": "pendente",
                "data": null,
                "creditos": 0,
                "foto": false
              },
              {
                "nome": "Maria Cecilia",
                "status": "pendente",
                "foto": false,
                "data": null,
                "creditos": 0
              }
            ]
          },
          {
            "id": "coord-raphael",
            "nome": "Raphael Freitas",
            "autores": [
              {
                "nome": "Jonas Nunes Coutinho",
                "status": "pendente",
                "data": null,
                "creditos": 0,
                "foto": false
              },
              {
                "nome": "Leize Lima de Oliveira",
                "status": "concluido",
                "data": "2026-06-27",
                "creditos": 1.26,
                "foto": true
              },
              {
                "nome": "Queila de Souza Santana",
                "status": "concluido",
                "data": "2026-06-27",
                "creditos": 1.31,
                "foto": true
              },
              {
                "nome": "Raphael Freitas",
                "status": "concluido",
                "foto": true,
                "data": "2026-07-07",
                "creditos": 7
              }
            ]
          },
          {
            "id": "coord-shirley",
            "nome": "Shirley Izabel - Isa Silva",
            "autores": [
              {
                "nome": "Ana P M D S Aguiar",
                "status": "concluido",
                "data": "2026-06-27",
                "creditos": 1.26,
                "foto": true
              },
              {
                "nome": "Carla Rojane",
                "status": "pendente",
                "data": null,
                "creditos": 0,
                "foto": false
              },
              {
                "nome": "Daniele de Resende Dias",
                "status": "concluido",
                "data": "2026-06-27",
                "creditos": 1.31,
                "foto": true
              },
              {
                "nome": "Diego Roberto",
                "status": "concluido",
                "data": "2026-07-08",
                "creditos": 2,
                "foto": true
              },
              {
                "nome": "Expedito Joao de Sales Filho",
                "status": "concluido",
                "data": "2026-06-27",
                "creditos": 1.26,
                "foto": true
              },
              {
                "nome": "Jair Barbosa",
                "status": "concluido",
                "data": "2026-06-27",
                "creditos": 1.26,
                "foto": true
              },
              {
                "nome": "Julio Cesar Rodrigues Vaz",
                "status": "concluido",
                "data": "2026-07-02",
                "creditos": 2,
                "foto": true
              },
              {
                "nome": "Luana Costa Barbosa Nicastro",
                "status": "concluido",
                "data": "2026-06-27",
                "creditos": 1.26,
                "foto": true
              },
              {
                "nome": "Maria Claudia Aparecida Satiro dos Santos",
                "status": "concluido",
                "data": "2026-06-27",
                "creditos": 1.26,
                "foto": true
              },
              {
                "nome": "Pamella Ferreira Leal",
                "status": "concluido",
                "data": "2026-06-27",
                "creditos": 1.26,
                "foto": true
              },
              {
                "nome": "Rosineide Maria de Paiva",
                "status": "pendente",
                "data": null,
                "creditos": 0,
                "foto": false
              },
              {
                "nome": "Silvana Amaro dos Santos",
                "status": "concluido",
                "data": "2026-06-27",
                "creditos": 1.26,
                "foto": true
              },
              {
                "nome": "Shirley Izabel - isa silva",
                "status": "concluido",
                "foto": true,
                "data": "2026-07-04",
                "creditos": 4
              },
              {
                "nome": "simone soares",
                "status": "concluido",
                "foto": true,
                "data": "2026-07-07",
                "creditos": 40
              },
              {
                "nome": "Roberto Guimaraes Belgran",
                "status": "concluido",
                "foto": true,
                "data": "2026-07-08",
                "creditos": 3
              }
            ]
          }
        ]
      },
      {
        "id": "empresarios-digital",
        "nome": "Empresários do Digital",
        "total_capitulos": 10,
        "coordenadores": [
          {
            "id": "coord-pedro-fiuza",
            "nome": "Pedro Fiuza",
            "autores": [
              {
                "nome": "Brendo Nogueira Carvalho",
                "status": "concluido",
                "data": "2026-06-27",
                "creditos": 4.94,
                "foto": true
              },
              {
                "nome": "Bruno Alexandre Capistrano de Irineu Silva",
                "status": "pendente",
                "data": null,
                "creditos": 0,
                "foto": false
              },
              {
                "nome": "Eduardo Fogaca",
                "status": "pendente",
                "data": null,
                "creditos": 0,
                "foto": false
              },
              {
                "nome": "Gabriel Charlyson Santana Pereira da Silva",
                "status": "concluido",
                "data": "2026-07-02",
                "creditos": 1,
                "foto": true
              },
              {
                "nome": "Gabriel Jesus Azevedo Santos",
                "status": "pendente",
                "data": null,
                "creditos": 0,
                "foto": false
              },
              {
                "nome": "Kelvin Campos",
                "status": "pendente",
                "data": null,
                "creditos": 0,
                "foto": false
              },
              {
                "nome": "Lana Caroline Marques Mota",
                "status": "concluido",
                "data": "2026-07-02",
                "creditos": 5,
                "foto": true
              },
              {
                "nome": "Matheus Goncalves Estevao",
                "status": "concluido",
                "data": "2026-07-02",
                "creditos": 2,
                "foto": true
              },
              {
                "nome": "Raiane Danielle de Souza Neponoceno Silva",
                "status": "concluido",
                "data": "2026-07-02",
                "creditos": 0,
                "foto": true
              },
              {
                "nome": "Walmir Rocha Lopes",
                "status": "concluido",
                "data": "2026-07-02",
                "creditos": 0,
                "foto": true
              },
              {
                "nome": "adriane miranda",
                "status": "concluido",
                "foto": true,
                "data": "2026-07-02",
                "creditos": 1
              },
              {
                "nome": "bruno daniel",
                "status": "concluido",
                "foto": true,
                "data": "2026-07-02",
                "creditos": 2
              },
              {
                "nome": "durval queiroz",
                "status": "concluido",
                "foto": true,
                "data": "2026-07-02",
                "creditos": 2
              },
              {
                "nome": "gabriel oliveira",
                "status": "concluido",
                "foto": true,
                "data": "2026-07-02",
                "creditos": 2
              },
              {
                "nome": "jeferson santos",
                "status": "concluido",
                "foto": false,
                "data": "2026-07-02",
                "creditos": 3
              },
              {
                "nome": "lylian mara",
                "status": "concluido",
                "foto": true,
                "data": "2026-07-02",
                "creditos": 11
              },
              {
                "nome": "Pedro Fiuza",
                "status": "concluido",
                "foto": true,
                "data": "2026-07-02",
                "creditos": 5
              },
              {
                "nome": "rafael miranda",
                "status": "concluido",
                "foto": true,
                "data": "2026-07-02",
                "creditos": 4
              },
              {
                "nome": "samuel brito",
                "status": "concluido",
                "foto": true,
                "data": "2026-07-02",
                "creditos": 0
              },
              {
                "nome": "Eduardo Fogaca--",
                "status": "pendente",
                "foto": false,
                "data": null,
                "creditos": 0
              },
              {
                "nome": "Gabriel Jesus Azevedo Santos ----",
                "status": "pendente",
                "foto": false,
                "data": null,
                "creditos": 0
              },
              {
                "nome": "Kelvin Campos---",
                "status": "pendente",
                "foto": false,
                "data": null,
                "creditos": 0
              },
              {
                "nome": "ana luisa",
                "status": "pendente",
                "foto": false,
                "data": null,
                "creditos": 0
              },
              {
                "nome": "antonio -dede",
                "status": "concluido",
                "foto": true,
                "data": "2026-07-08",
                "creditos": 1
              },
              {
                "nome": "caio zalt",
                "status": "concluido",
                "foto": true,
                "data": "2026-07-08",
                "creditos": 2
              },
              {
                "nome": "cleo",
                "status": "pendente",
                "foto": false,
                "data": null,
                "creditos": 0
              },
              {
                "nome": "erica janaina",
                "status": "pendente",
                "foto": false,
                "data": null,
                "creditos": 0
              },
              {
                "nome": "gabriel- presente jorge",
                "status": "pendente",
                "foto": false,
                "data": null,
                "creditos": 0
              },
              {
                "nome": "jessica",
                "status": "pendente",
                "foto": false,
                "data": null,
                "creditos": 0
              },
              {
                "nome": "joci",
                "status": "pendente",
                "foto": false,
                "data": null,
                "creditos": 0
              },
              {
                "nome": "lucy",
                "status": "pendente",
                "foto": false,
                "data": null,
                "creditos": 0
              },
              {
                "nome": "mylene aparecida",
                "status": "pendente",
                "foto": false,
                "data": null,
                "creditos": 0
              },
              {
                "nome": "nayara",
                "status": "pendente",
                "foto": false,
                "data": null,
                "creditos": 0
              },
              {
                "nome": "priscila - presente jorge",
                "status": "pendente",
                "foto": false,
                "data": null,
                "creditos": 0
              },
              {
                "nome": "raiane - presente jorge",
                "status": "pendente",
                "foto": false,
                "data": null,
                "creditos": 0
              },
              {
                "nome": "roberto gomes",
                "status": "concluido",
                "foto": true,
                "data": "2026-07-07",
                "creditos": 5
              },
              {
                "nome": "shirlay",
                "status": "concluido",
                "foto": true,
                "data": "2026-07-07",
                "creditos": 10
              },
              {
                "nome": "thamires",
                "status": "pendente",
                "foto": false,
                "data": null,
                "creditos": 0
              },
              {
                "nome": "chico jr",
                "status": "concluido",
                "foto": true,
                "data": "2026-07-04",
                "creditos": 5
              },
              {
                "nome": "erlania borges",
                "status": "concluido",
                "foto": true,
                "data": "2026-07-04",
                "creditos": 2
              },
              {
                "nome": "gabriel alcantara",
                "status": "concluido",
                "foto": true,
                "data": "2026-07-04",
                "creditos": 2
              },
              {
                "nome": "hosana brandao",
                "status": "concluido",
                "foto": true,
                "data": "2026-07-04",
                "creditos": 9
              },
              {
                "nome": "jhulie campello",
                "status": "concluido",
                "foto": true,
                "data": "2026-07-04",
                "creditos": 8
              },
              {
                "nome": "leandro rispoli",
                "status": "concluido",
                "foto": true,
                "data": "2026-07-04",
                "creditos": 4
              },
              {
                "nome": "luciana dos santos souza",
                "status": "concluido",
                "foto": true,
                "data": "2026-07-04",
                "creditos": 11
              },
              {
                "nome": "luiz felipe ferreira",
                "status": "concluido",
                "foto": true,
                "data": "2026-07-04",
                "creditos": 2
              },
              {
                "nome": "luiz murilho",
                "status": "concluido",
                "foto": true,
                "data": "2026-07-04",
                "creditos": 9
              },
              {
                "nome": "otto ferreira",
                "status": "concluido",
                "foto": true,
                "data": "2026-07-04",
                "creditos": 0
              },
              {
                "nome": "priscila rocha",
                "status": "concluido",
                "foto": true,
                "data": "2026-07-04",
                "creditos": 4
              },
              {
                "nome": "rademar de sa",
                "status": "concluido",
                "foto": true,
                "data": "2026-07-04",
                "creditos": 3
              },
              {
                "nome": "ricardo da costa verissimo",
                "status": "concluido",
                "foto": true,
                "data": "2026-07-04",
                "creditos": 17
              },
              {
                "nome": "roberta veras",
                "status": "concluido",
                "foto": true,
                "data": "2026-07-07",
                "creditos": 3
              },
              {
                "nome": "roger marquez",
                "status": "concluido",
                "foto": true,
                "data": "2026-07-04",
                "creditos": 5
              },
              {
                "nome": "gabriel garcez",
                "status": "concluido",
                "foto": true,
                "data": "2026-07-07",
                "creditos": 0
              },
              {
                "nome": "gabriel intenso",
                "status": "concluido",
                "foto": true,
                "data": "2026-07-07",
                "creditos": 1
              },
              {
                "nome": "joao adolfo",
                "status": "concluido",
                "foto": true,
                "data": "2026-07-07",
                "creditos": 2
              },
              {
                "nome": "luis fernandes",
                "status": "concluido",
                "foto": true,
                "data": "2026-07-07",
                "creditos": 1
              },
              {
                "nome": "marcio antunes",
                "status": "concluido",
                "foto": true,
                "data": "2026-07-07",
                "creditos": 1
              },
              {
                "nome": "marquinhos malaquias",
                "status": "concluido",
                "foto": true,
                "data": "2026-07-07",
                "creditos": 2
              },
              {
                "nome": "ramon silveira",
                "status": "concluido",
                "foto": true,
                "data": "2026-07-07",
                "creditos": 3
              }
            ]
          }
        ]
      },
      {
        "id": "entre-chaves-sonhos",
        "nome": "Entre Chaves e Sonhos",
        "total_capitulos": 0,
        "coordenadores": []
      },
      {
        "id": "gigantes-so-mulheres",
        "nome": "Gigantes Nascem da Queda - So Mulheres",
        "total_capitulos": 28,
        "coordenadores": [
          {
            "id": "coord-cida-montijo",
            "nome": "COORD-Cida Montijo",
            "autores": [
              {
                "nome": "Andrea Angelini de Oliveira",
                "status": "concluido",
                "foto": true,
                "data": "2026-07-08",
                "creditos": 5
              },
              {
                "nome": "Edna Oliveira Ferreira Araujo",
                "status": "concluido",
                "foto": true,
                "data": "2026-07-08",
                "creditos": 1
              },
              {
                "nome": "Gleysse Cunha Paolinelli",
                "status": "concluido",
                "foto": true,
                "data": "2026-07-08",
                "creditos": 6
              },
              {
                "nome": "Sandra da Silva Santos",
                "status": "pendente",
                "foto": false,
                "data": null,
                "creditos": 0
              },
              {
                "nome": "Silmara Guadarin",
                "status": "pendente",
                "foto": false,
                "data": null,
                "creditos": 0
              }
            ]
          },
          {
            "id": "coord-isabel-tonetto",
            "nome": "COORD-Isabel Tonetto",
            "autores": [
              {
                "nome": "Diulena Maria de Sousa",
                "status": "concluido",
                "foto": true,
                "data": "2026-06-30",
                "creditos": 1.0
              },
              {
                "nome": "Sara Lisa Cipresso Pereira",
                "status": "concluido",
                "foto": true,
                "data": "2026-06-30",
                "creditos": 15.0
              },
              {
                "nome": "isabel tonetto",
                "status": "concluido",
                "foto": true,
                "data": "2026-07-02",
                "creditos": 0
              }
            ]
          },
          {
            "id": "coord-juraci",
            "nome": "COORD-Juraci",
            "autores": [
              {
                "nome": "Joana Darck de Oliveira Pires",
                "status": "pendente",
                "foto": false,
                "data": null,
                "creditos": 0
              }
            ]
          },
          {
            "id": "coord-meri-mogoga",
            "nome": "COORD-Meri Mogoga",
            "autores": [
              {
                "nome": "Adriane",
                "status": "concluido",
                "foto": true,
                "data": "2026-07-08",
                "creditos": 8
              },
              {
                "nome": "Amanda Carlos Gomes Bravo",
                "status": "pendente",
                "foto": false,
                "data": null,
                "creditos": 0
              },
              {
                "nome": "Ana Laura Vargas",
                "status": "concluido",
                "foto": false,
                "data": "2026-07-02",
                "creditos": 3
              },
              {
                "nome": "Iara Bergel",
                "status": "pendente",
                "foto": false,
                "data": null,
                "creditos": 0
              },
              {
                "nome": "Madalena Albuquerque",
                "status": "pendente",
                "foto": false,
                "data": null,
                "creditos": 0
              },
              {
                "nome": "Marli Alejandro",
                "status": "concluido",
                "foto": true,
                "data": "2026-07-02",
                "creditos": 2
              },
              {
                "nome": "Rosangela Ferreira de Andrade",
                "status": "concluido",
                "foto": true,
                "data": "2026-07-08",
                "creditos": 8
              },
              {
                "nome": "Sonia Alves",
                "status": "concluido",
                "foto": true,
                "data": "2026-07-07",
                "creditos": 1
              },
              {
                "nome": "Tania Maia",
                "status": "concluido",
                "foto": false,
                "data": "2026-07-08",
                "creditos": 3
              },
              {
                "nome": "Valquiria Silva",
                "status": "concluido",
                "foto": true,
                "data": "2026-07-02",
                "creditos": 9
              },
              {
                "nome": "Veronica Germano Martins Araujo",
                "status": "concluido",
                "foto": true,
                "data": "2026-07-02",
                "creditos": 17
              },
              {
                "nome": "Meri Mogoga",
                "status": "concluido",
                "foto": true,
                "data": "2026-07-08",
                "creditos": 0
              }
            ]
          },
          {
            "id": "coord-rosilene-almeida",
            "nome": "COORD-Rosilene Almeida",
            "autores": [
              {
                "nome": "Bernadete Cavalcante Nascimento",
                "status": "concluido",
                "foto": true,
                "data": "2026-06-30",
                "creditos": 2.0
              },
              {
                "nome": "Emile Rosana de Lima Lima",
                "status": "concluido",
                "foto": true,
                "data": "2026-06-30",
                "creditos": 6.0
              },
              {
                "nome": "Lucila Anunciacao Correia",
                "status": "concluido",
                "foto": true,
                "data": "2026-06-30",
                "creditos": 9.0
              },
              {
                "nome": "Maria de Fatima Hanaque Campos",
                "status": "concluido",
                "foto": true,
                "data": "2026-06-30",
                "creditos": 8.0
              },
              {
                "nome": "Saint Clair Cezar",
                "status": "concluido",
                "foto": true,
                "data": "2026-06-30",
                "creditos": 3.0
              },
              {
                "nome": "Virginia Oliveira Santos",
                "status": "concluido",
                "foto": true,
                "data": "2026-06-30",
                "creditos": 2.0
              },
              {
                "nome": "rosilene araujo",
                "status": "concluido",
                "foto": true,
                "data": "2026-07-02",
                "creditos": 0
              }
            ]
          },
          {
            "id": "indicacoes-maria-cecilia",
            "nome": "INDICACOES-Maria Cecilia",
            "autores": [
              {
                "nome": "Yasmin Bastos Rosa",
                "status": "pendente",
                "foto": false,
                "data": null,
                "creditos": 0
              },
              {
                "nome": "maria cecilia",
                "status": "pendente",
                "foto": false,
                "data": null,
                "creditos": 0
              }
            ]
          },
          {
            "id": "indicacoes-maria-lucia",
            "nome": "INDICACOES-Maria Lucia",
            "autores": [
              {
                "nome": "Claudilene Leite Gomes",
                "status": "pendente",
                "foto": false,
                "data": null,
                "creditos": 0
              }
            ]
          }
        ]
      },
      {
        "id": "herois-v10-sp",
        "nome": "Herois Implacaveis V10 SP",
        "total_capitulos": 26,
        "coordenadores": [
          {
            "id": "coord-alice",
            "nome": "COORD-Alice",
            "autores": [
              {
                "nome": "Leomar Oliveira Campos",
                "status": "concluido",
                "foto": true,
                "data": "2026-07-04",
                "creditos": 3
              }
            ]
          },
          {
            "id": "coord-caio-henrique-quintero-castelo-branco",
            "nome": "COORD-Caio Henrique Quintero Castelo Branco",
            "autores": [
              {
                "nome": "Lucio Jose de Azevedo Lucena",
                "status": "concluido",
                "foto": true,
                "data": "2026-07-04",
                "creditos": 11
              },
              {
                "nome": "Luiza Maria Aragao Pontes",
                "status": "concluido",
                "foto": true,
                "data": "2026-07-04",
                "creditos": 3
              },
              {
                "nome": "Maria Gorete Oliveira de Sousa",
                "status": "concluido",
                "foto": true,
                "data": "2026-07-04",
                "creditos": 7
              },
              {
                "nome": "Caio Henrique Quinderé Castello Branco",
                "status": "concluido",
                "foto": true,
                "data": "2026-07-04",
                "creditos": 6
              }
            ]
          },
          {
            "id": "coord-luis-caversan",
            "nome": "COORD-Luis Caversan",
            "autores": [
              {
                "nome": "Ederson Alves Machado",
                "status": "concluido",
                "foto": true,
                "data": "2026-07-04",
                "creditos": 2
              },
              {
                "nome": "Gisele Alves Costanza Caversan",
                "status": "concluido",
                "foto": true,
                "data": "2026-07-04",
                "creditos": 2
              },
              {
                "nome": "Kaique Nunes Pereira",
                "status": "concluido",
                "foto": true,
                "data": "2026-07-04",
                "creditos": 5
              },
              {
                "nome": "Ketilyn Karina Ortega Canzano",
                "status": "concluido",
                "foto": true,
                "data": "2026-07-04",
                "creditos": 1
              },
              {
                "nome": "Maerley P Costa",
                "status": "concluido",
                "foto": true,
                "data": "2026-07-04",
                "creditos": 6
              },
              {
                "nome": "Marcus Vinicius Severo",
                "status": "concluido",
                "foto": true,
                "data": "2026-07-04",
                "creditos": 7
              },
              {
                "nome": "Taisa Fatima Casimiro Sanches",
                "status": "concluido",
                "foto": true,
                "data": "2026-07-04",
                "creditos": 9
              },
              {
                "nome": "Teresa Cristina Lala dos Santos Faria",
                "status": "concluido",
                "foto": true,
                "data": "2026-07-04",
                "creditos": 6
              },
              {
                "nome": "Vanessa de Paula Moreira Oliveira",
                "status": "concluido",
                "foto": true,
                "data": "2026-07-04",
                "creditos": 2
              },
              {
                "nome": "luis felipe caversan",
                "status": "concluido",
                "foto": true,
                "data": "2026-07-04",
                "creditos": 3
              },
              {
                "nome": "nielsen carvalho lima",
                "status": "concluido",
                "foto": true,
                "data": "2026-07-07",
                "creditos": 11
              },
              {
                "nome": "simone rufino",
                "status": "concluido",
                "foto": true,
                "data": "2026-07-07",
                "creditos": 42
              },
              {
                "nome": "patricia nunes romano",
                "status": "concluido",
                "foto": true,
                "data": "2026-07-08",
                "creditos": 1
              }
            ]
          },
          {
            "id": "coord-neriane-conceicao",
            "nome": "COORD-Neriane Conceicao",
            "autores": [
              {
                "nome": "Claudia Maria Eberhardt Thomas",
                "status": "concluido",
                "foto": true,
                "data": "2026-07-04",
                "creditos": 4
              },
              {
                "nome": "Francieli Giraldon Hammerschmitt",
                "status": "concluido",
                "foto": true,
                "data": "2026-06-30",
                "creditos": 2.0
              },
              {
                "nome": "Meg Andrade",
                "status": "concluido",
                "foto": true,
                "data": "2026-06-30",
                "creditos": 2.0
              },
              {
                "nome": "Rosmaite Immich",
                "status": "concluido",
                "foto": true,
                "data": "2026-06-30",
                "creditos": 4.0
              },
              {
                "nome": "Walda Shirley Paes Moura de Menezes",
                "status": "concluido",
                "foto": true,
                "data": "2026-07-04",
                "creditos": 19
              },
              {
                "nome": "neriane",
                "status": "concluido",
                "foto": true,
                "data": "2026-07-04",
                "creditos": 10
              }
            ]
          },
          {
            "id": "coord-rademar",
            "nome": "COORD-Rademar",
            "autores": [
              {
                "nome": "Rademar",
                "status": "pendente",
                "foto": false,
                "data": null,
                "creditos": 0
              }
            ]
          },
          {
            "id": "coord-rosane-menegueli",
            "nome": "COORD-Rosane Menegueli",
            "autores": [
              {
                "nome": "Ediana Cristina Nascimento",
                "status": "concluido",
                "foto": true,
                "data": "2026-07-04",
                "creditos": 3
              },
              {
                "nome": "Liliane Carneiro Costa",
                "status": "concluido",
                "foto": true,
                "data": "2026-07-04",
                "creditos": 22
              },
              {
                "nome": "Livia Carolina Arruda Andrade",
                "status": "pendente",
                "foto": false,
                "data": null,
                "creditos": 0
              },
              {
                "nome": "Marcia Lima",
                "status": "concluido",
                "foto": true,
                "data": "2026-06-30",
                "creditos": 2.0
              },
              {
                "nome": "Maria Brigida Maia Matos",
                "status": "concluido",
                "foto": true,
                "data": "2026-07-07",
                "creditos": 10
              },
              {
                "nome": "Rosangela Fraga de Souza",
                "status": "concluido",
                "foto": true,
                "data": "2026-06-30",
                "creditos": 6.0
              },
              {
                "nome": "Sabrina Santos da Conceicao",
                "status": "concluido",
                "foto": true,
                "data": "2026-07-04",
                "creditos": 41
              },
              {
                "nome": "rosane menegueli",
                "status": "concluido",
                "foto": true,
                "data": "2026-07-02",
                "creditos": 0
              },
              {
                "nome": "Maria Silvaneide",
                "status": "concluido",
                "foto": true,
                "data": "2026-07-04",
                "creditos": 9
              },
              {
                "nome": "lucia costa",
                "status": "concluido",
                "foto": true,
                "data": "2026-07-04",
                "creditos": 4
              },
              {
                "nome": "katia calisto",
                "status": "concluido",
                "foto": true,
                "data": "2026-07-07",
                "creditos": 1
              }
            ]
          }
        ]
      },
      {
        "id": "mulheres-essenciais",
        "nome": "Mulheres Essenciais",
        "total_capitulos": 27,
        "coordenadores": [
          {
            "id": "coord-lu-santos",
            "nome": "COORD-Lu Santos",
            "autores": [
              {
                "nome": "Ana Claudia Silva Melo",
                "status": "concluido",
                "foto": true,
                "data": "2026-07-02",
                "creditos": 0
              },
              {
                "nome": "Bruna Francielly Rodrigues Feres",
                "status": "concluido",
                "foto": true,
                "data": "2026-06-30",
                "creditos": 4.0
              },
              {
                "nome": "Cleonice Vilma dos Santos Almeida",
                "status": "concluido",
                "foto": true,
                "data": "2026-07-02",
                "creditos": 0
              },
              {
                "nome": "Glaucia",
                "status": "pendente",
                "foto": false,
                "data": null,
                "creditos": 0
              },
              {
                "nome": "Katia Barbosa de Lima Rocha",
                "status": "concluido",
                "foto": true,
                "data": "2026-07-02",
                "creditos": 2
              },
              {
                "nome": "Lorena Rayalla",
                "status": "concluido",
                "foto": true,
                "data": "2026-07-02",
                "creditos": 0
              },
              {
                "nome": "Luciane Johanson Lelis da Silva",
                "status": "concluido",
                "foto": true,
                "data": "2026-07-02",
                "creditos": 7
              },
              {
                "nome": "Lucilene Felipe dos Santos",
                "status": "concluido",
                "foto": true,
                "data": "2026-07-02",
                "creditos": 1
              },
              {
                "nome": "Nelise Duarte de Sousa Taia",
                "status": "concluido",
                "foto": true,
                "data": "2026-07-07",
                "creditos": 22
              },
              {
                "nome": "Renata",
                "status": "pendente",
                "foto": true,
                "data": null,
                "creditos": 0
              },
              {
                "nome": "Renata rosa",
                "status": "concluido",
                "foto": true,
                "data": "2026-07-02",
                "creditos": 0
              },
              {
                "nome": "Graziela lack",
                "status": "concluido",
                "foto": true,
                "data": "2026-07-04",
                "creditos": 3
              },
              {
                "nome": "Juliana Alves",
                "status": "concluido",
                "foto": true,
                "data": "2026-07-04",
                "creditos": 14
              },
              {
                "nome": "Liliane e Jane",
                "status": "concluido",
                "foto": true,
                "data": "2026-07-04",
                "creditos": 3
              },
              {
                "nome": "SHÍRLEY FREITAS",
                "status": "concluido",
                "foto": true,
                "data": "2026-07-04",
                "creditos": 13
              },
              {
                "nome": "Stefhanny Souza",
                "status": "concluido",
                "foto": true,
                "data": "2026-07-04",
                "creditos": 0
              },
              {
                "nome": "claudia pires",
                "status": "concluido",
                "foto": true,
                "data": "2026-07-07",
                "creditos": 1
              },
              {
                "nome": "laiza danyelle",
                "status": "concluido",
                "foto": true,
                "data": "2026-07-07",
                "creditos": 11
              }
            ]
          },
          {
            "id": "coord-rose-rozendo",
            "nome": "COORD-Rose Rozendo",
            "autores": [
              {
                "nome": "Constantina Abreu",
                "status": "concluido",
                "foto": true,
                "data": "2026-06-30",
                "creditos": 2.0
              },
              {
                "nome": "Gildete Farias Conceicao",
                "status": "concluido",
                "foto": true,
                "data": "2026-06-30",
                "creditos": 9.0
              },
              {
                "nome": "Isabel Elias",
                "status": "concluido",
                "foto": true,
                "data": "2026-06-30",
                "creditos": 6.0
              },
              {
                "nome": "Katia Regina",
                "status": "concluido",
                "foto": true,
                "data": "2026-07-07",
                "creditos": 2
              },
              {
                "nome": "Regina Celia Santos Rocha",
                "status": "concluido",
                "foto": true,
                "data": "2026-06-30",
                "creditos": 7.0
              },
              {
                "nome": "Simoni Luduvice",
                "status": "concluido",
                "foto": true,
                "data": "2026-06-30",
                "creditos": 8.0
              },
              {
                "nome": "Zilanda Amim Palacin - 2 capitulo",
                "status": "concluido",
                "foto": true,
                "data": "2026-07-02",
                "creditos": 4
              },
              {
                "nome": "rose rozendo",
                "status": "concluido",
                "foto": true,
                "data": "2026-07-02",
                "creditos": 0
              },
              {
                "nome": "naiane pereira ramos",
                "status": "concluido",
                "foto": true,
                "data": "2026-07-04",
                "creditos": 3
              },
              {
                "nome": "sandra barcellos",
                "status": "concluido",
                "foto": true,
                "data": "2026-07-04",
                "creditos": 15
              },
              {
                "nome": "rose rodrigues",
                "status": "concluido",
                "foto": true,
                "data": "2026-07-07",
                "creditos": 0
              }
            ]
          },
          {
            "id": "coord-zenaira",
            "nome": "COORD-Zenaira",
            "autores": [
              {
                "nome": "Atenilda da Silva Alves",
                "status": "concluido",
                "foto": true,
                "data": "2026-06-30",
                "creditos": 6.0
              },
              {
                "nome": "Ivelise Amorim",
                "status": "pendente",
                "foto": false,
                "data": null,
                "creditos": 0
              },
              {
                "nome": "Joana Carmen do Nascimento Machado",
                "status": "pendente",
                "foto": false,
                "data": null,
                "creditos": 0
              },
              {
                "nome": "Maria Carmelita Nery Rodrigues",
                "status": "concluido",
                "foto": true,
                "data": "2026-07-02",
                "creditos": 3
              },
              {
                "nome": "Maria Silvana de Sousa Santos",
                "status": "concluido",
                "foto": true,
                "data": "2026-06-30",
                "creditos": 4.0
              },
              {
                "nome": "Meryellen Da Gama e Silva dos Santos",
                "status": "concluido",
                "foto": true,
                "data": "2026-06-30",
                "creditos": 7.0
              },
              {
                "nome": "Raquel Garcia Coelho",
                "status": "concluido",
                "foto": true,
                "data": "2026-07-07",
                "creditos": 4
              },
              {
                "nome": "Sandra Nascimento",
                "status": "pendente",
                "foto": false,
                "data": null,
                "creditos": 0
              },
              {
                "nome": "erica janaina",
                "status": "pendente",
                "foto": false,
                "data": null,
                "creditos": 0
              },
              {
                "nome": "zenaria mariana",
                "status": "concluido",
                "foto": true,
                "data": "2026-07-07",
                "creditos": 16
              }
            ]
          }
        ]
      },
      {
        "id": "poder-conhecer-direitos-pt",
        "nome": "O Poder de Conhecer Seus Direitos - PT",
        "total_capitulos": 23,
        "coordenadores": [
          {
            "id": "coord-rubens",
            "nome": "COORD-Rubens",
            "autores": [
              {
                "nome": "Alexandre de Menezes Simao",
                "status": "pendente",
                "foto": false,
                "data": null,
                "creditos": 0
              },
              {
                "nome": "Lidiane Praxedes de Oliveira",
                "status": "concluido",
                "foto": true,
                "data": "2026-07-08",
                "creditos": 10
              },
              {
                "nome": "Liliane Ikenaga",
                "status": "pendente",
                "foto": false,
                "data": null,
                "creditos": 0
              },
              {
                "nome": "Maria das Dores",
                "status": "pendente",
                "foto": false,
                "data": null,
                "creditos": 0
              },
              {
                "nome": "Rubens Neuber de Souza Junior",
                "status": "pendente",
                "foto": false,
                "data": null,
                "creditos": 0
              }
            ]
          },
          {
            "id": "coord-thiago-jordao",
            "nome": "COORD-Thiago Jordao",
            "autores": [
              {
                "nome": "Cibeli Marques Bannitz Egger",
                "status": "concluido",
                "foto": true,
                "data": "2026-06-30",
                "creditos": 6.0
              },
              {
                "nome": "Flavia Magalhaes Artilheiro",
                "status": "concluido",
                "foto": true,
                "data": "2026-07-07",
                "creditos": 18
              },
              {
                "nome": "Flavia Magalhaes Artilheiro - 2 capitulo",
                "status": "concluido",
                "foto": true,
                "data": "2026-07-07",
                "creditos": 12
              },
              {
                "nome": "Jeanine Nunes Romano",
                "status": "concluido",
                "foto": true,
                "data": "2026-06-30",
                "creditos": 7.0
              },
              {
                "nome": "Shanasis Emanuelle de Oliveira Squillaci",
                "status": "concluido",
                "foto": true,
                "data": "2026-06-30",
                "creditos": 3.0
              },
              {
                "nome": "Shanasis Emanuelle de Oliveira Squillaci - 2 capitulo",
                "status": "pendente",
                "foto": true,
                "data": null,
                "creditos": 0
              },
              {
                "nome": "hellen claudia",
                "status": "concluido",
                "foto": true,
                "data": "2026-07-02",
                "creditos": 2
              },
              {
                "nome": "diego henrique",
                "status": "concluido",
                "foto": true,
                "data": "2026-07-04",
                "creditos": 1
              },
              {
                "nome": "jeferson",
                "status": "concluido",
                "foto": true,
                "data": "2026-07-07",
                "creditos": 1
              }
            ]
          },
          {
            "nome": "COORD-Pollyanna Quites",
            "autores": [
              {
                "nome": "Ana Elisa Silva Braz",
                "status": "concluido",
                "foto": true,
                "data": "2026-07-02",
                "creditos": 0
              },
              {
                "nome": "Claudia Marques de Macedo",
                "status": "concluido",
                "foto": true,
                "data": "2026-07-02",
                "creditos": 0
              },
              {
                "nome": "Perla Christiane de Araujo",
                "status": "concluido",
                "foto": true,
                "data": "2026-07-02",
                "creditos": 0
              },
              {
                "nome": "Sabrina Fernanda Baeta Tergilene",
                "status": "concluido",
                "foto": true,
                "data": "2026-07-02",
                "creditos": 0
              },
              {
                "nome": "poliana quites",
                "status": "concluido",
                "foto": true,
                "data": "2026-07-08",
                "creditos": 0
              },
              {
                "nome": "karolina emanuel",
                "status": "concluido",
                "foto": true,
                "data": "2026-07-07",
                "creditos": 3
              }
            ]
          }
        ]
      },
      {
        "id": "os-caminhos-excelencia-humana",
        "nome": "Os Caminhos para a Excelência Humana",
        "coordenadores": [
          {
            "nome": "COORD-Carla Rojane",
            "autores": [
              {
                "nome": "Gisele Piccoli König",
                "status": "concluido",
                "foto": true,
                "data": "2026-07-03",
                "creditos": 2
              }
            ]
          },
          {
            "nome": "COORD-Renata Castello Branco",
            "autores": [
              {
                "nome": "Ana Cacilda de Castro",
                "status": "concluido",
                "foto": true,
                "data": "2026-07-03",
                "creditos": 6
              },
              {
                "nome": "Ana Kelly Santos Lima",
                "status": "concluido",
                "foto": true,
                "data": "2026-07-07",
                "creditos": 13
              },
              {
                "nome": "Carla Ottoni",
                "status": "concluido",
                "foto": true,
                "data": "2026-07-03",
                "creditos": 2
              },
              {
                "nome": "Cléo Lima",
                "status": "concluido",
                "foto": true,
                "data": "2026-07-07",
                "creditos": 14
              },
              {
                "nome": "Cristina Correia Barreto",
                "status": "concluido",
                "foto": false,
                "data": "2026-07-03",
                "creditos": 3
              },
              {
                "nome": "Jamile Quézia Carvalho",
                "status": "concluido",
                "foto": true,
                "data": "2026-07-03",
                "creditos": 3
              },
              {
                "nome": "Leide Santana Cerqueira",
                "status": "concluido",
                "foto": true,
                "data": "2026-07-03",
                "creditos": 27
              },
              {
                "nome": "Livia Carolina Arruda Andrade",
                "status": "concluido",
                "foto": true,
                "data": "2026-07-03",
                "creditos": 5
              },
              {
                "nome": "Maira Tavares de Souza",
                "status": "concluido",
                "foto": true,
                "data": "2026-07-04",
                "creditos": 3
              },
              {
                "nome": "Mona Liz Abreu",
                "status": "concluido",
                "foto": true,
                "data": "2026-07-08",
                "creditos": 17
              },
              {
                "nome": "Monica Maria Bezerra da Silva",
                "status": "concluido",
                "foto": true,
                "data": "2026-07-03",
                "creditos": 12
              },
              {
                "nome": "Neusa Silva Brandão",
                "status": "concluido",
                "foto": true,
                "data": "2026-07-03",
                "creditos": 0
              },
              {
                "nome": "Renata Castello Brandão",
                "status": "concluido",
                "foto": true,
                "data": "2026-07-03",
                "creditos": 9
              },
              {
                "nome": "Rosangela Xavier",
                "status": "concluido",
                "foto": true,
                "data": "2026-07-03",
                "creditos": 1
              },
              {
                "nome": "Telma Marinho Barreto Bastos",
                "status": "concluido",
                "foto": true,
                "data": "2026-07-03",
                "creditos": 19
              },
              {
                "nome": "Vanessa Garcia Aragão",
                "status": "concluido",
                "foto": true,
                "data": "2026-07-03",
                "creditos": 2
              },
              {
                "nome": "Wagner Ferreira Moreira Klein",
                "status": "concluido",
                "foto": true,
                "data": "2026-07-03",
                "creditos": 1
              },
              {
                "nome": "daniele pio",
                "status": "concluido",
                "foto": true,
                "data": "2026-07-07",
                "creditos": 6
              }
            ]
          },
          {
            "nome": "COORD-Sônia",
            "autores": [
              {
                "nome": "Adelice Minetto",
                "status": "concluido",
                "foto": true,
                "data": "2026-07-03",
                "creditos": 3
              },
              {
                "nome": "Cristiane de Farias Alves",
                "status": "pendente",
                "foto": false,
                "data": null,
                "creditos": 0
              },
              {
                "nome": "Dra. Ana Paula Nunes",
                "status": "pendente",
                "foto": false,
                "data": null,
                "creditos": 0
              },
              {
                "nome": "Gabriela Ottoni",
                "status": "concluido",
                "foto": true,
                "data": "2026-07-03",
                "creditos": 16
              },
              {
                "nome": "Jane Nogueira Lima",
                "status": "concluido",
                "foto": true,
                "data": "2026-07-03",
                "creditos": 0
              },
              {
                "nome": "Luana Oliveira Chiminacio Pereira",
                "status": "pendente",
                "foto": false,
                "data": null,
                "creditos": 0
              },
              {
                "nome": "Marcela Silva Chaves de Paula Lavezo",
                "status": "concluido",
                "foto": true,
                "data": "2026-07-03",
                "creditos": 11
              },
              {
                "nome": "Marcia Priscila Leite de Lima",
                "status": "concluido",
                "foto": true,
                "data": "2026-07-03",
                "creditos": 26
              },
              {
                "nome": "Marlene Almeida",
                "status": "concluido",
                "foto": true,
                "data": "2026-07-03",
                "creditos": 14
              },
              {
                "nome": "Priscila Gessica",
                "status": "concluido",
                "foto": true,
                "data": "2026-07-03",
                "creditos": 6
              },
              {
                "nome": "Simone Cherlie",
                "status": "concluido",
                "foto": true,
                "data": "2026-07-03",
                "creditos": 9
              },
              {
                "nome": "Sônia",
                "status": "concluido",
                "foto": true,
                "data": "2026-07-03",
                "creditos": 3
              },
              {
                "nome": "Tânia",
                "status": "pendente",
                "foto": false,
                "data": null,
                "creditos": 0
              },
              {
                "nome": "moises santuario",
                "status": "concluido",
                "foto": true,
                "data": "2026-07-07",
                "creditos": 4
              }
            ]
          }
        ]
      }
    ]
  },
  "robert": {
    "nome": "Robert",
    "cor": "#EF4444",
    "livros": [
      {
        "id": "herois-vol10",
        "nome": "HEROIS VOL 10",
        "total_capitulos": 16,
        "coordenadores": [
          {
            "id": "coord-silva",
            "nome": "COORD-SILVA",
            "autores": [
              {
                "nome": "[Autor 1]",
                "status": "pendente",
                "data": null,
                "creditos": 0
              },
              {
                "nome": "[Autor 2]",
                "status": "pendente",
                "data": null,
                "creditos": 0
              }
            ]
          }
        ]
      }
    ]
  }
}